{
  "id": "C-ATTACH-SYNC-6",
  "type": "attach",
  "version": "v1",
  "priority": "attach",
  "status": "active",
  "scope": [
    "adapter/test",
    "adapter/src"
  ],
  "stage": "ci",
  "rule": "Calling config_sync without a corresponding commit is test-only and must not be treated as a product write path; production synchronization follows C-ATTACH-SYNC-2.",
  "gate_refs": [
    "GATE-ATTACH-SYNC-PROD"
  ],
  "blocking": true,
  "owner": "subtask-b-eng",
  "evidence": [
    "架构方案选择记录.md",
    "docs/reports/contract-gate-report.json"
  ],
  "deprecate": null,
  "implementations": [
    {
      "gate_id": "GATE-ATTACH-SYNC-PROD",
      "runner": "python",
      "entry": "tools/scripts/gates/check_attach_sync_prod_paths.py",
      "entry_kind": "script"
    }
  ]
}
